odoo/addons/stock_grn/README.rst
odoo/addons/stock_grn/__init__.py
odoo/addons/stock_grn/__manifest__.py
odoo/addons/stock_grn/data/stock_grn.xml
odoo/addons/stock_grn/i18n/es.po
odoo/addons/stock_grn/i18n/it.po
odoo/addons/stock_grn/i18n/stock_grn.pot
odoo/addons/stock_grn/models/__init__.py
odoo/addons/stock_grn/models/stock_grn.py
odoo/addons/stock_grn/models/stock_grn_type.py
odoo/addons/stock_grn/models/stock_move.py
odoo/addons/stock_grn/models/stock_picking.py
odoo/addons/stock_grn/models/stock_picking_type.py
odoo/addons/stock_grn/readme/CONTRIBUTORS.rst
odoo/addons/stock_grn/readme/DESCRIPTION.rst
odoo/addons/stock_grn/readme/USAGE.rst
odoo/addons/stock_grn/security/ir.model.access.csv
odoo/addons/stock_grn/security/ir_rule.xml
odoo/addons/stock_grn/static/description/icon.png
odoo/addons/stock_grn/static/description/index.html
odoo/addons/stock_grn/tests/__init__.py
odoo/addons/stock_grn/tests/test_stock_grn.py
odoo/addons/stock_grn/views/stock_grn_type_views.xml
odoo/addons/stock_grn/views/stock_grn_views.xml
odoo/addons/stock_grn/views/stock_move_views.xml
odoo/addons/stock_grn/views/stock_picking_type_views.xml
odoo/addons/stock_grn/views/stock_picking_views.xml
odoo_addon_stock_grn-16.0.1.1.0.2.dist-info/METADATA
odoo_addon_stock_grn-16.0.1.1.0.2.dist-info/WHEEL
odoo_addon_stock_grn-16.0.1.1.0.2.dist-info/top_level.txt
odoo_addon_stock_grn-16.0.1.1.0.2.dist-info/RECORD
